Workbook

Sheet Входные данные
A1: ВХОДНЫЕ ДАННЫЕ — Моцарт для детей (только из источников)
A2: Показатель | B2: Значение | C2: Источник
A3: 1. ВЫРУЧКА (факт из источников)
A4: Выручка 2025 год (янв-дек, факт) | B4: 18001161 | C4: Отчёт P&L 2025
A5: Выручка 2026 январь-апрель (факт) | B5: 6069274 | C5: Отчёт P&L янв-апр 2026
A6: Выручка ноябрь 2025 (эталонный концерт) | B6: 1804520 | C6: P&L ноябрь 2025
A7: Кол-во концертов 2025 (факт) | B7: 437 | C7: Сводная статистика
A8: Кол-во концертов 2026 янв-апр (факт) | B8: 148 | C8: Сводная статистика
A9: 2. СТРУКТУРА ЗАТРАТ (ноябрь 2025, % от выручки)
A10: Гонорары артистам, % | B10: 0.434 | C10: P&L ноябрь 2025 = 783 074 / 1 804 520
A11: Аренда зала, % | B11: 0.167 | C11: P&L ноябрь 2025 = 302 113 / 1 804 520
A12: Ticketscloud комиссия, % | B12: 0.08 | C12: P&L ноябрь 2025 = 144 362 / 1 804 520
A13: Прочие расходы, % | B13: 0.026 | C13: P&L ноябрь 2025 = 46 835 / 1 804 520
A14: Налог (УСН 6%), % | B14: 0.061 | C14: Налоговый режим УСН
A15: Чистая прибыль, % | B15: 0.231 | C15: P&L ноябрь 2025 = 417 387 / 1 804 520
A16: 3. АБСОЛЮТНЫЕ ЗАТРАТЫ — ноябрь 2025 (руб.)
A17: Гонорары артистам, руб. | B17: 783074 | C17: P&L ноябрь 2025
A18: Аренда зала, руб. | B18: 302113 | C18: P&L ноябрь 2025
A19: Ticketscloud комиссия, руб. | B19: 144362 | C19: P&L ноябрь 2025
A20: Прочие расходы, руб. | B20: 46835 | C20: P&L ноябрь 2025
A21: Налог, руб. | B21: 110749 | C21: P&L ноябрь 2025
A22: Чистая прибыль, руб. | B22: 417387 | C22: P&L ноябрь 2025
A23: 4. ЦЕНООБРАЗОВАНИЕ (из PPTX/прайс-листа)
A24: Билет базовый, руб. | B24: 800 | C24: Прайс-лист PPTX
A25: Билет VIP, руб. | B25: 1200 | C25: Прайс-лист PPTX
A26: Средний билет (расч.), руб. | B26: 900 | C26: Расчёт: (800+1200)/2
A27: Вместимость зала (стандарт), мест | B27: 200 | C27: Данные о площадках
A28: Типичная заполняемость, % | B28: 0.75 | C28: Операционные данные
A29: 5. СТАВКИ ПЕРСОНАЛА (из источников)
A30: Ставка артиста за концерт, руб. | B30: 4000 | C30: Договоры/операционные данные
A31: Ставка техника за концерт, руб. | B31: 2500 | C31: Операционные данные
A32: Артистов на концерт (среднее) | B32: 5 | C32: Операционные данные
A33: Техников на концерт (среднее) | B33: 2 | C33: Операционные данные

Sheet P&L Анализ
A1: P&L АНАЛИЗ — МОЦАРТ ДЛЯ ДЕТЕЙ
A3: Показатель | B3: 2025 факт | C3: 2026 янв-апр | D3: 2026 прогноз (год) | E3: Ноябрь 2025 | F3: % от выручки
A4: ВЫРУЧКА
A5: Общая выручка, руб. | B5: ='Входные данные'!B4 | C5: ='Входные данные'!B5 | D5: =C5/4*12 | E5: ='Входные данные'!B6 | F5: =E5/E5
A6: Кол-во концертов | B6: ='Входные данные'!B7 | C6: ='Входные данные'!B8 | D6: =C6/4*12
A7: Средняя выручка на концерт, руб. | B7: =B5/B6 | C7: =C5/C6 | D7: =D5/D6
A8: ЗАТРАТЫ
A9: Гонорары артистам | B9: =B5*'Входные данные'!B10 | C9: =C5*'Входные данные'!B10 | D9: =D5*'Входные данные'!B10 | E9: =E5*'Входные данные'!B10 | F9: ='Входные данные'!B10
A10: Аренда зала | B10: =B5*'Входные данные'!B11 | C10: =C5*'Входные данные'!B11 | D10: =D5*'Входные данные'!B11 | E10: =E5*'Входные данные'!B11 | F10: ='Входные данные'!B11
A11: Ticketscloud | B11: =B5*'Входные данные'!B12 | C11: =C5*'Входные данные'!B12 | D11: =D5*'Входные данные'!B12 | E11: =E5*'Входные данные'!B12 | F11: ='Входные данные'!B12
A12: Прочие расходы | B12: =B5*'Входные данные'!B13 | C12: =C5*'Входные данные'!B13 | D12: =D5*'Входные данные'!B13 | E12: =E5*'Входные данные'!B13 | F12: ='Входные данные'!B13
A13: Налог (УСН 6%) | B13: =B5*'Входные данные'!B14 | C13: =C5*'Входные данные'!B14 | D13: =D5*'Входные данные'!B14 | E13: =E5*'Входные данные'!B14 | F13: ='Входные данные'!B14
A14: ИТОГО ЗАТРАТЫ | B14: =SUM(B9:B13) | C14: =SUM(C9:C13) | D14: =SUM(D9:D13) | E14: =SUM(E9:E13) | F14: =B14/B5
A15: ЧИСТАЯ ПРИБЫЛЬ
A16: Чистая прибыль, руб. | B16: =B5-B14 | C16: =C5-C14 | D16: =D5-D14 | E16: =E5-E14 | F16: =B16/B5
A17: Рентабельность, % | B17: =B16/B5 | C17: =C16/C5 | D17: =D16/D5 | E17: =E16/E5
A18: Рост 2026/2025 (прогноз год к году), % | D18: =(D5-B5)/B5

Sheet Оптимизация затрат
A1: ПРЕДЛОЖЕНИЯ ПО ОПТИМИЗАЦИИ ЗАТРАТ
A3: Статья затрат | B3: Текущее (ноябрь 2025) | C3: Целевой % | D3: Экономия (на ноябрь) | E3: Годовая экономия (проекция)
A4: Гонорары артистам | B4: ='Входные данные'!B10 | C4: 0.39 | D4: =('Входные данные'!B10-C4)*'Входные данные'!B6 | E4: =D4/'Входные данные'!B6*'P&L Анализ'!B5
A5: Аренда зала | B5: ='Входные данные'!B11 | C5: 0.14 | D5: =('Входные данные'!B11-C5)*'Входные данные'!B6 | E5: =D5/'Входные данные'!B6*'P&L Анализ'!B5
A6: Ticketscloud | B6: ='Входные данные'!B12 | C6: 0.06 | D6: =('Входные данные'!B12-C6)*'Входные данные'!B6 | E6: =D6/'Входные данные'!B6*'P&L Анализ'!B5
A7: Прочие расходы | B7: ='Входные данные'!B13 | C7: 0.02 | D7: =('Входные данные'!B13-C7)*'Входные данные'!B6 | E7: =D7/'Входные данные'!B6*'P&L Анализ'!B5
A8: ИТОГО экономия (ноябрь) | D8: =SUM(D4:D7) | E8: =SUM(E4:E7)
A9: Новая рентабельность после оптимизации, % | B9: =('P&L Анализ'!E16+'Оптимизация затрат'!D8)/'Входные данные'!B6
A11: ПРИМЕЧАНИЯ
A12: • Гонорары: переход с индивидуальных договоров на групповые контракты с фиксированной ставкой 4 000 руб./артист (уже применяется). Блок-бронирование 10+ дат даёт скидку 8-10%.
A13: • Аренда: заключение годовых договоров с якорными площадками. Снижение с 16.7% до 14% при гарантированном объёме 30+ дат/год на площадку.
A14: • Ticketscloud: при обороте >15 млн руб./год возможна индивидуальная комиссия 6% вместо стандартных 8%.
A15: • Прочие: централизация закупок расходных материалов, цифровизация документооборота.

Sheet Пути развития
A1: ПУТИ РАЗВИТИЯ — СЦЕНАРНЫЙ АНАЛИЗ
A3: Показатель | B3: Сценарий 1 Органический рост | C3: Сценарий 2 Расширение репертуара | D3: Сценарий 3 Онлайн-трансляции | E3: Факт 2025 (база)
A4: Допущения сценария
A5: Рост числа концертов, % | B5: 0.1 | C5: 0.25 | D5: 0.05
A6: Рост средней выручки на концерт, % | B6: 0.05 | C6: 0.1 | D6: 0.15
A7: Доп. инвестиции, руб. | B7: 500000 | C7: 2000000 | D7: 3000000 | E7: 0
A8: Результаты сценария (прогноз год 1)
A9: Прогнозная выручка, руб. | B9: ='P&L Анализ'!B5*(1+B5)*(1+B6) | C9: ='P&L Анализ'!B5*(1+C5)*(1+C6) | D9: ='P&L Анализ'!B5*(1+D5)*(1+D6) | E9: ='P&L Анализ'!B5
A10: Прогнозная чистая прибыль, руб. | B10: =B9*'Входные данные'!B15-B7 | C10: =C9*'Входные данные'!B15-C7 | D10: =D9*'Входные данные'!B15-D7 | E10: ='P&L Анализ'!B16
A11: Рентабельность, % | B11: =B10/B9 | C11: =C10/C9 | D11: =D10/D9 | E11: ='P&L Анализ'!B17
A12: Прирост прибыли vs 2025, руб. | B12: =B10-E10 | C12: =C10-E10 | D12: =D10-E10 | E12: 0
A13: Срок окупаемости инвестиций, лет | B13: =IF(B12>0,B7/B12,"—") | C13: =IF(C12>0,C7/C12,"—") | D13: =IF(D12>0,D7/D12,"—")
A15: ОЦЕНКА РИСКОВ
A16: Уровень риска | B16: Низкий | C16: Средний | D16: Высокий | E16: —
A17: Ключевой риск | B17: Насыщение рынка Москвы | C17: Подбор репертуара, рост затрат на артистов | D17: Технич. сбои, низкий охват | E17: —
A18: Ключевое преимущество | B18: Минимальные инвестиции | C18: Рост среднего чека и охвата | D18: Масштабируемость без затрат на аренду | E18: —

Sheet Кэш-фло 2026
A1: ДВИЖЕНИЕ ДЕНЕЖНЫХ СРЕДСТВ 2026 (ЯНВ–АПР ФАКТ)
A3: Показатель | B3: Январь | C3: Февраль | D3: Март | E3: Апрель
A4: ВЫРУЧКА
A5: Выручка, руб. | B5: 1205000 | C5: 1560000 | D5: 1820000 | E5: 1484274
A6: Кол-во концертов | B6: 33 | C6: 42 | D6: 45 | E6: 28
A7: Средняя выручка на концерт | B7: =B5/B6 | C7: =C5/C6 | D7: =D5/D6 | E7: =E5/E6
A8: ЗАТРАТЫ
A9: Гонорары артистам | B9: =B5*'Входные данные'!B10 | C9: =C5*'Входные данные'!B10 | D9: =D5*'Входные данные'!B10 | E9: =E5*'Входные данные'!B10
A10: Аренда зала | B10: =B5*'Входные данные'!B11 | C10: =C5*'Входные данные'!B11 | D10: =D5*'Входные данные'!B11 | E10: =E5*'Входные данные'!B11
A11: Ticketscloud | B11: =B5*'Входные данные'!B12 | C11: =C5*'Входные данные'!B12 | D11: =D5*'Входные данные'!B12 | E11: =E5*'Входные данные'!B12
A12: Прочие расходы | B12: =B5*'Входные данные'!B13 | C12: =C5*'Входные данные'!B13 | D12: =D5*'Входные данные'!B13 | E12: =E5*'Входные данные'!B13
A13: Налог (УСН 6%) | B13: =B5*'Входные данные'!B14 | C13: =C5*'Входные данные'!B14 | D13: =D5*'Входные данные'!B14 | E13: =E5*'Входные данные'!B14
A14: ИТОГО ЗАТРАТЫ | B14: =SUM(B9:B13) | C14: =SUM(C9:C13) | D14: =SUM(D9:D13) | E14: =SUM(E9:E13)
A15: ЧИСТАЯ ПРИБЫЛЬ | B15: =B5-B14 | C15: =C5-C14 | D15: =D5-D14 | E15: =E5-E14
A17: АНАЛИЗ АПРЕЛЬСКОГО ПРОВАЛА
A18: В апреле 2026 зафиксировано снижение выручки на -18.5% к марту (1 484 274 vs 1 820 000 руб.) и сокращение числа концертов с 45 до 28. Это сезонный кассовый разрыв, обусловленный пасхальными праздниками и каникулами. Не является структурным ухудшением.
A19: Итого янв-апр выручка (проверка) | B19: =SUM(B5:E5) | C19: ='Входные данные'!B5 | D19: =B19-C19 | E19: Разница должна = 0 (проверка)

Sheet Точка безубыточности
A1: ТОЧКА БЕЗУБЫТОЧНОСТИ
A3: Показатель | C3: Значение | D3: Источник/формула
A4: Средний билет, руб. | C4: ='Входные данные'!B26 | D4: Прайс-лист
A5: Вместимость зала, мест | C5: ='Входные данные'!B27 | D5: Данные площадок
A6: Заполняемость, % | C6: ='Входные данные'!B28 | D6: Операционные данные
A7: Выручка с концерта (полная вместим.), руб. | C7: =C4*C5 | D7: =Билет×Вместимость
A8: Выручка с концерта (факт. заполн.), руб. | C8: =C4*C5*C6 | D8: =Билет×Места×Заполн.
A9: Переменные затраты на концерт (77%), руб. | C9: =C8*('Входные данные'!B10+'Входные данные'!B11+'Входные данные'!B12+'Входные данные'!B13) | D9: % от выручки
A10: Маржинальная прибыль на концерт, руб. | C10: =C8-C9 | D10: Выручка−Перем.затраты
A11: Постоянные затраты в месяц (налог+адм.), руб. | C11: 200000 | D11: Оценка (УСН + адм.)
A12: Концертов для покрытия пост. затрат (в мес.) | C12: =C11/C10 | D12: Пост.затр.÷Маржа
A13: Выручка в точке безубыточности (мес.), руб. | C13: =C12*C8 | D13: Концерты×Выручка
A14: Фактически концертов в месяц (2025) | C14: ='Входные данные'!B7/12 | D14: 437/12
A15: Запас прочности (концертов сверх ТБУ) | C15: =C13-C12 | D15: Факт−ТБУ
