Workbook

Sheet Входные данные
A1: ВХОДНЫЕ ДАННЫЕ — Моцарт для детей
A2: Показатель | B2: Значение | C2: Источник
A3: ВЫРУЧКА (факт)
A4: Выручка 2025 год (факт), руб. | B4: 18001161 | C4: Отчёт P&L 2025
A5: Выручка 2026 янв–апр (факт), руб. | B5: 6069274 | C5: Отчёт P&L янв–апр 2026
A6: Выручка ноябрь 2025 (эталон), руб. | B6: 1804520 | C6: P&L ноябрь 2025
A7: Кол-во концертов 2025 (факт) | B7: 437 | C7: Статистика
A8: Кол-во концертов 2026 янв–апр (факт) | B8: 148 | C8: Статистика
A9: ПАРАМЕТРЫ ЗАЛА И БИЛЕТОВ
A10: Вместимость зала, мест | B10: 35 | C10: Фактические данные площадок
A11: Средний билет, руб. | B11: 2800 | C11: Прайс-лист (источники)
A12: Заполняемость (типовая), % | B12: 0.75 | C12: Операционные данные
A13: Выручка с концерта (полн. зал), руб. | B13: =B10*B11 | C13: =Вместимость×Билет
A14: Выручка с концерта (факт. 75%), руб. | B14: =B10*B11*B12 | C14: =Вмест.×Билет×Заполн.
A15: СТРУКТУРА ЗАТРАТ (% от выручки, ноябрь 2025)
A16: Гонорары артистам, % | B16: 0.434 | C16: P&L ноябрь 2025: 783 074 / 1 804 520
A17: Аренда зала, % | B17: 0.167 | C17: P&L ноябрь 2025: 302 113 / 1 804 520
A18: Ticketscloud, % | B18: 0.08 | C18: P&L ноябрь 2025: 144 362 / 1 804 520
A19: Прочие расходы, % | B19: 0.026 | C19: P&L ноябрь 2025: 46 835 / 1 804 520
A20: Налог (УСН 6%), % | B20: 0.061 | C20: Налоговый режим
A21: Чистая прибыль, % | B21: 0.231 | C21: P&L ноябрь 2025: 417 387 / 1 804 520
A22: УПРАВЛЕНЧЕСКАЯ КОМАНДА
A23: Руководитель | B23: 25000 | C23: Фиксированная ставка (без %, без надбавок)
A24: Менеджер выездных мероприятий | B24: 25000 | C24: Фиксированная ставка (без %, без надбавок)
A25: SMM-специалист | B25: 25000 | C25: Фиксированная ставка (без %, без надбавок)
A26: Концертный директор | B26: 25000 | C26: Фиксированная ставка (без %, без надбавок)
A27: Куратор концертов | B27: 25000 | C27: Фиксированная ставка (без %, без надбавок)
A28: Специалист по сайту | B28: 25000 | C28: Фиксированная ставка (без %, без надбавок)
A29: Координатор программ | B29: 25000 | C29: Фиксированная ставка (без %, без надбавок)
A30: ИТОГО команда, руб./мес. | B30: =SUM(B23:B29) | C30: =7 × 25 000
A31: ИТОГО команда, руб./год | B31: =B30*12 | C31: =месяц × 12

Sheet P&L Анализ
A1: P&L АНАЛИЗ — МОЦАРТ ДЛЯ ДЕТЕЙ
A3: Показатель | B3: 2025 факт | C3: 2026 янв–апр | D3: 2026 прогноз (год) | E3: Ноябрь 2025 | F3: % (ноябрь)
A4: ВЫРУЧКА
A5: Выручка, руб. | B5: ='Входные данные'!B4 | C5: ='Входные данные'!B5 | D5: =C5/4*12 | E5: ='Входные данные'!B6 | F5: =E5/E5
A6: Кол-во концертов | B6: ='Входные данные'!B7 | C6: ='Входные данные'!B8 | D6: =C6/4*12
A7: Средняя выручка/концерт, руб. | B7: =B5/B6 | C7: =C5/C6 | D7: =D5/D6
A8: ЗАТРАТЫ (операционные)
A9: Гонорары артистам | B9: =B5*'Входные данные'!B16 | C9: =C5*'Входные данные'!B16 | D9: =D5*'Входные данные'!B16 | E9: =E5*'Входные данные'!B16 | F9: ='Входные данные'!B16
A10: Аренда зала | B10: =B5*'Входные данные'!B17 | C10: =C5*'Входные данные'!B17 | D10: =D5*'Входные данные'!B17 | E10: =E5*'Входные данные'!B17 | F10: ='Входные данные'!B17
A11: Ticketscloud | B11: =B5*'Входные данные'!B18 | C11: =C5*'Входные данные'!B18 | D11: =D5*'Входные данные'!B18 | E11: =E5*'Входные данные'!B18 | F11: ='Входные данные'!B18
A12: Прочие расходы | B12: =B5*'Входные данные'!B19 | C12: =C5*'Входные данные'!B19 | D12: =D5*'Входные данные'!B19 | E12: =E5*'Входные данные'!B19 | F12: ='Входные данные'!B19
A13: Налог (УСН 6%) | B13: =B5*'Входные данные'!B20 | C13: =C5*'Входные данные'!B20 | D13: =D5*'Входные данные'!B20 | E13: =E5*'Входные данные'!B20 | F13: ='Входные данные'!B20
A14: УПРАВЛЕНЧЕСКАЯ КОМАНДА
A15: Команда (7 чел. × 25 000), руб./мес. | B15: ='Входные данные'!B31 | C15: ='Входные данные'!B30*4 | D15: ='Входные данные'!B31 | E15: ='Входные данные'!B30
A16: ИТОГО ЗАТРАТЫ | B16: =SUM(B9:B13)+B15 | C16: =SUM(C9:C13)+C15 | D16: =SUM(D9:D13)+D15 | E16: =SUM(E9:E13)+E15 | F16: =B16/B5
A17: ЧИСТАЯ ПРИБЫЛЬ
A18: Чистая прибыль, руб. | B18: =B5-B16 | C18: =C5-C16 | D18: =D5-D16 | E18: =E5-E16 | F18: =B18/B5
A19: Рентабельность, % | B19: =B18/B5 | C19: =C18/C5 | D19: =D18/D5 | E19: =E18/E5

Sheet Команда
A1: УПРАВЛЕНЧЕСКАЯ КОМАНДА
A2: Должность | B2: Ставка, руб./мес. | C2: Год, руб.
A3: Руководитель | B3: ='Входные данные'!B23 | C3: =B3*12
A4: Менеджер выездных мероприятий | B4: ='Входные данные'!B24 | C4: =B4*12
A5: SMM-специалист | B5: ='Входные данные'!B25 | C5: =B5*12
A6: Концертный директор | B6: ='Входные данные'!B26 | C6: =B6*12
A7: Куратор концертов | B7: ='Входные данные'!B27 | C7: =B7*12
A8: Специалист по сайту | B8: ='Входные данные'!B28 | C8: =B8*12
A9: Координатор программ | B9: ='Входные данные'!B29 | C9: =B9*12
A10: ИТОГО в месяц | B10: =SUM(B3:B9) | C10: =SUM(C3:C9)
A11: Проверка (из Входных данных) | B11: ='Входные данные'!B30 | C11: ='Входные данные'!B31

Sheet Точка безубыточности
A1: ТОЧКА БЕЗУБЫТОЧНОСТИ
A2: Параметр | C2: Значение / формула
A3: Вместимость зала, мест | C3: ='Входные данные'!B10
A4: Средний билет, руб. | C4: ='Входные данные'!B11
A5: Заполняемость, % | C5: ='Входные данные'!B12
A6: Выручка с концерта (75%), руб. | C6: =B3*B4*B5
A7: Переменные затраты (70,7%), % | C7: ='Входные данные'!B16+'Входные данные'!B17+'Входные данные'!B18+'Входные данные'!B19
A8: Переменные затраты, руб./концерт | C8: =B7*B6
A9: Маржинальная прибыль, руб./концерт | C9: =B6-B8
A10: Пост. затраты: налог+адм., руб./мес. | C10: 200000
A11: Пост. затраты: команда, руб./мес. | C11: ='Входные данные'!B30
A12: ИТОГО постоянные затраты, руб./мес. | C12: =B10+B11
A13: ТБУ (концертов/мес.) | C13: =B12/B9
A14: Фактически концертов/мес. (2025) | C14: ='Входные данные'!B7/12
A15: Запас прочности (концертов/мес.) | C15: =B14-B13

Sheet Оптимизация затрат
A1: ОПТИМИЗАЦИЯ ЗАТРАТ
A2: Статья | B2: Текущий % | C2: Целевой % | D2: Экономия (ноябрь) | E2: Годовая экономия
A3: Гонорары артистам | B3: ='Входные данные'!B16 | C3: 0.39 | D3: =('Входные данные'!B16-C3)*'Входные данные'!B6 | E3: =D3/'Входные данные'!B6*'P&L Анализ'!B5
A4: Аренда зала | B4: ='Входные данные'!B17 | C4: 0.14 | D4: =('Входные данные'!B17-C4)*'Входные данные'!B6 | E4: =D4/'Входные данные'!B6*'P&L Анализ'!B5
A5: Ticketscloud | B5: ='Входные данные'!B18 | C5: 0.06 | D5: =('Входные данные'!B18-C5)*'Входные данные'!B6 | E5: =D5/'Входные данные'!B6*'P&L Анализ'!B5
A6: Прочие расходы | B6: ='Входные данные'!B19 | C6: 0.02 | D6: =('Входные данные'!B19-C6)*'Входные данные'!B6 | E6: =D6/'Входные данные'!B6*'P&L Анализ'!B5
A7: ИТОГО экономия | D7: =SUM(D3:D6) | E7: =SUM(E3:E6)
